zsync/CLI.py
zsync/Config.py
zsync/SyncEngine.py
zsync/ZSync.py
zsync/__init__.py
ZSync-1.3.dist-info/LICENSE
ZSync-1.3.dist-info/METADATA
ZSync-1.3.dist-info/WHEEL
ZSync-1.3.dist-info/entry_points.txt
ZSync-1.3.dist-info/top_level.txt
ZSync-1.3.dist-info/RECORD
