Metadata-Version: 2.1
Name: ZSync
Version: 1.3
Summary: a cli tool for syncing local files
Home-page: https://github.com/LittleHeroZZZX/ZSync
Author: ZhouXin
Author-email: zhou.xin2000@outlook.com
License: MIT
Requires-Python: >=3.12
License-File: LICENSE
Requires-Dist: dotmap
Requires-Dist: tqdm
Requires-Dist: PyYAML
